Orange3_WorldHappiness-0.1.12-py3.11-nspkg.pth
Orange3_WorldHappiness-0.1.12.data/data/help/orange3-worldhappiness/.buildinfo
Orange3_WorldHappiness-0.1.12.data/data/help/orange3-worldhappiness/genindex.html
Orange3_WorldHappiness-0.1.12.data/data/help/orange3-worldhappiness/index.html
Orange3_WorldHappiness-0.1.12.data/data/help/orange3-worldhappiness/objects.inv
Orange3_WorldHappiness-0.1.12.data/data/help/orange3-worldhappiness/search.html
Orange3_WorldHappiness-0.1.12.data/data/help/orange3-worldhappiness/searchindex.js
Orange3_WorldHappiness-0.1.12.data/data/help/orange3-worldhappiness/_images/socioeconomic-indices.png
Orange3_WorldHappiness-0.1.12.data/data/help/orange3-worldhappiness/_sources/index.rst.txt
Orange3_WorldHappiness-0.1.12.data/data/help/orange3-worldhappiness/_sources/widgets/socioeconomicindices.md.txt
Orange3_WorldHappiness-0.1.12.data/data/help/orange3-worldhappiness/_static/_sphinx_javascript_frameworks_compat.js
Orange3_WorldHappiness-0.1.12.data/data/help/orange3-worldhappiness/_static/basic.css
Orange3_WorldHappiness-0.1.12.data/data/help/orange3-worldhappiness/_static/custom.css
Orange3_WorldHappiness-0.1.12.data/data/help/orange3-worldhappiness/_static/doctools.js
Orange3_WorldHappiness-0.1.12.data/data/help/orange3-worldhappiness/_static/documentation_options.js
Orange3_WorldHappiness-0.1.12.data/data/help/orange3-worldhappiness/_static/file.png
Orange3_WorldHappiness-0.1.12.data/data/help/orange3-worldhappiness/_static/jquery.js
Orange3_WorldHappiness-0.1.12.data/data/help/orange3-worldhappiness/_static/language_data.js
Orange3_WorldHappiness-0.1.12.data/data/help/orange3-worldhappiness/_static/minus.png
Orange3_WorldHappiness-0.1.12.data/data/help/orange3-worldhappiness/_static/plus.png
Orange3_WorldHappiness-0.1.12.data/data/help/orange3-worldhappiness/_static/pygments.css
Orange3_WorldHappiness-0.1.12.data/data/help/orange3-worldhappiness/_static/searchtools.js
Orange3_WorldHappiness-0.1.12.dist-info/LICENSE.txt
Orange3_WorldHappiness-0.1.12.dist-info/METADATA
Orange3_WorldHappiness-0.1.12.dist-info/WHEEL
Orange3_WorldHappiness-0.1.12.dist-info/entry_points.txt
Orange3_WorldHappiness-0.1.12.dist-info/namespace_packages.txt
Orange3_WorldHappiness-0.1.12.dist-info/top_level.txt
Orange3_WorldHappiness-0.1.12.dist-info/RECORD
