Metadata-Version: 2.1
Name: Orange3-WorldHappiness
Version: 0.1.12
Summary: Orange3 add-on for retrieving socioeconomic data
Home-page: http://orange.biolab.si/download
Author: Bioinformatics Laboratory, FRI UL
Author-email: contact@orange.biolab.si
License: GPL3+
Keywords: orange3 add-on,orange3-world-happiness
Classifier: Development Status :: 3 - Alpha
Classifier: Intended Audience :: Education
Classifier: Intended Audience :: Science/Research
Classifier: License :: OSI Approved :: GNU General Public License v3 or later (GPLv3+)
Classifier: Programming Language :: Python :: 3 :: Only
License-File: LICENSE.txt
Requires-Dist: Orange3 >=3.31
Requires-Dist: pandas
Requires-Dist: pymongo
Requires-Dist: wbgapi
Requires-Dist: dnspython
Provides-Extra: doc
Requires-Dist: sphinx ; extra == 'doc'
Requires-Dist: recommonmark ; extra == 'doc'
Requires-Dist: sphinx-rtd-theme ; extra == 'doc'
Requires-Dist: docutils ; extra == 'doc'
Provides-Extra: test
Requires-Dist: coverage ; extra == 'test'
